example/toy/make_test_data.py
example/toy/run_model.py
example/toy2/make_test_data.py
example/toy2/run_model.py
kolossus/__init__.py
kolossus/extract.py
kolossus/kolossus.py
kolossus/main.py
kolossus/panel.py
kolossus/aprkh_utils/__init__.py
kolossus/aprkh_utils/listops.py
kolossus/aprkh_utils/seqio.py
kolossus/aprkh_utils/stringops.py
kolossus/aprkh_utils/decorators/__init__.py
kolossus/aprkh_utils/decorators/batch_utils.py
kolossus/aprkh_utils/decorators/time_utils.py
kolossus/aprkh_utils/misc/__init__.py
kolossus/aprkh_utils/misc/codon_table.py
kolossus/models/Network.py
kolossus/models/__init__.py
kolossus/models/load_model.py
kolossus/utils/__init__.py
kolossus/utils/batch_utils.py
kolossus/utils/conditional_returns.py
kolossus/utils/parse_fasta.py
kolossus/utils/read_data.py
kolossus/utils/seq_to_embedding.py
kolossus/utils/seqops.py
kolossus/utils/warnings.py
kolossus/utils/write_fasta.py
kolossus-1.0.6.dist-info/METADATA
kolossus-1.0.6.dist-info/WHEEL
kolossus-1.0.6.dist-info/entry_points.txt
kolossus-1.0.6.dist-info/top_level.txt
kolossus-1.0.6.dist-info/RECORD
