Metadata-Version: 2.4
Name: kolossus
Version: 1.0.6
Summary: Predict kinase-substrate interactions.
Author-email: Aditya Parekh <aditya.parekh@duke.edu>, Kanchan Jha <kanchan.jha@duke.edu>
Project-URL: Homepage, https://github.com/rohitsinghlab/KolossuS
Project-URL: Bug Tracker, https://github.com/rohitsinghlab/KolossuS/issues
Classifier: Programming Language :: Python :: 3
Classifier: License :: OSI Approved :: MIT License
Classifier: Operating System :: OS Independent
Requires-Dist: setuptools
Requires-Dist: numpy
Requires-Dist: scikit-learn
Requires-Dist: PyYaml
Requires-Dist: torch
Requires-Dist: biopython
Requires-Dist: h5py
Requires-Dist: transformers
Requires-Dist: fair-esm
